LICENSE
README.md
setup.py
appspec_yaml_leaks.egg-info/PKG-INFO
appspec_yaml_leaks.egg-info/SOURCES.txt
appspec_yaml_leaks.egg-info/dependency_links.txt
appspec_yaml_leaks.egg-info/entry_points.txt
appspec_yaml_leaks.egg-info/requires.txt
appspec_yaml_leaks.egg-info/top_level.txt
appspecyamlleaks/__init__.py
appspecyamlleaks/main.py
appspecyamlleaks/includes/__init__.py
appspecyamlleaks/includes/bot.py
appspecyamlleaks/includes/filereader.py
appspecyamlleaks/includes/scan.py
appspecyamlleaks/includes/writefile.py
appspecyamlleaks/utils/__init__.py
appspecyamlleaks/utils/configure.py
appspecyamlleaks/utils/const.py
appspecyamlleaks/utils/helpers.py
appspecyamlleaks/utils/status.py